README.rst
setup.py
crimg/__init__.py
crimg/api.py
crimg/bin.py
crimg.egg-info/PKG-INFO
crimg.egg-info/SOURCES.txt
crimg.egg-info/dependency_links.txt
crimg.egg-info/entry_points.txt
crimg.egg-info/requires.txt
crimg.egg-info/top_level.txt