Metadata-Version: 1.0
Name: crimg
Version: 0.0.3
Summary: Crop and resize an image without aspect ratio distortion.
Home-page: https://github.com/codeif/crimg
Author: codeif
Author-email: me@codeif.com
License: MIT
Platform: UNKNOWN
